pyoppversion/__init__.py
pyoppversion/consts.py
pyoppversion-3.4.2.dist-info/LICENSE
pyoppversion-3.4.2.dist-info/METADATA
pyoppversion-3.4.2.dist-info/WHEEL
pyoppversion-3.4.2.dist-info/top_level.txt
pyoppversion-3.4.2.dist-info/RECORD
