Metadata-Version: 2.1
Name: pyoppversion
Version: 3.4.2
Summary: UNKNOWN
Home-page: https://github.com/ludeeus/pyoppversion
Author: Paul Caston
Author-email: paul@caston.id.au
License: UNKNOWN
Platform: UNKNOWN
Classifier: Programming Language :: Python :: 3
Classifier: License :: OSI Approved :: MIT License
Classifier: Operating System :: OS Independent
Requires-Dist: aiohttp
Requires-Dist: async-timeout (<=3.0.1)
Requires-Dist: pytest-runner
Requires-Dist: semantic-version
